st_pandas_text_editor/__init__.py
st_pandas_text_editor/frontend/build/asset-manifest.json
st_pandas_text_editor/frontend/build/bootstrap.min.css
st_pandas_text_editor/frontend/build/index.html
st_pandas_text_editor/frontend/build/static/css/2.9b7094a5.chunk.css
st_pandas_text_editor/frontend/build/static/css/2.9b7094a5.chunk.css.map
st_pandas_text_editor/frontend/build/static/css/main.c21eaae6.chunk.css
st_pandas_text_editor/frontend/build/static/css/main.c21eaae6.chunk.css.map
st_pandas_text_editor/frontend/build/static/js/2.4b9686c7.chunk.js
st_pandas_text_editor/frontend/build/static/js/2.4b9686c7.chunk.js.LICENSE.txt
st_pandas_text_editor/frontend/build/static/js/2.4b9686c7.chunk.js.map
st_pandas_text_editor/frontend/build/static/js/2.817968fe.chunk.js
st_pandas_text_editor/frontend/build/static/js/2.817968fe.chunk.js.LICENSE.txt
st_pandas_text_editor/frontend/build/static/js/2.817968fe.chunk.js.map
st_pandas_text_editor/frontend/build/static/js/2.ecfcc7a3.chunk.js
st_pandas_text_editor/frontend/build/static/js/2.ecfcc7a3.chunk.js.LICENSE.txt
st_pandas_text_editor/frontend/build/static/js/2.ecfcc7a3.chunk.js.map
st_pandas_text_editor/frontend/build/static/js/main.168a4d94.chunk.js
st_pandas_text_editor/frontend/build/static/js/main.168a4d94.chunk.js.map
st_pandas_text_editor/frontend/build/static/js/main.57164539.chunk.js
st_pandas_text_editor/frontend/build/static/js/main.57164539.chunk.js.map
st_pandas_text_editor/frontend/build/static/js/main.7e37a4e5.chunk.js
st_pandas_text_editor/frontend/build/static/js/main.7e37a4e5.chunk.js.map
st_pandas_text_editor/frontend/build/static/js/main.baa131a3.chunk.js
st_pandas_text_editor/frontend/build/static/js/main.baa131a3.chunk.js.map
st_pandas_text_editor/frontend/build/static/js/runtime-main.624f085e.js
st_pandas_text_editor/frontend/build/static/js/runtime-main.624f085e.js.map
streamlit_pandas_text_editor-0.0.6.dist-info/LICENSE
streamlit_pandas_text_editor-0.0.6.dist-info/METADATA
streamlit_pandas_text_editor-0.0.6.dist-info/WHEEL
streamlit_pandas_text_editor-0.0.6.dist-info/top_level.txt
streamlit_pandas_text_editor-0.0.6.dist-info/RECORD
