Metadata-Version: 2.1
Name: streamlit-pandas-text-editor
Version: 0.0.6
Summary: Rich Text Editor with customizable Dropdown Options for Streamlit
Home-page: 
Author: Anonymous
Author-email: anonymous_paper_submission@outlook.com
Requires-Python: >=3.6
License-File: LICENSE
Requires-Dist: streamlit (>=0.63)
